medal_api/__init__.py
medal_api-0.1.5.dist-info/LICENSE
medal_api-0.1.5.dist-info/METADATA
medal_api-0.1.5.dist-info/WHEEL
medal_api-0.1.5.dist-info/top_level.txt
medal_api-0.1.5.dist-info/RECORD
