Metadata-Version: 2.1
Name: medal-api
Version: 0.1.5
Home-page: https://github.com/gianklug/medal-api
Author: Gian Klug
Author-email: gian.klug@ict-scouts.ch
License-File: LICENSE
